CHANGES
LICENSE
MANIFEST.in
README.md
setup.py
cider/__init__.py
cider/_cli.py
cider/_lib.py
cider/_osx.m
cider/_sh.py
cider/_tty.py
cider/core.py
cider/exceptions.py
cider.egg-info/PKG-INFO
cider.egg-info/SOURCES.txt
cider.egg-info/dependency_links.txt
cider.egg-info/entry_points.txt
cider.egg-info/requires.txt
cider.egg-info/top_level.txt
tests/__init__.py
tests/_lib.py
tests/test_cli.py
tests/test_core.py
tests/test_sh.py