Metadata-Version: 1.1
Name: cider
Version: 1.1.6
Summary: Hassle-free bootstrapping using Homebrew.
Home-page: https://github.com/msanders/cider
Author: Michael Sanders
Author-email: michael [at] msanders [dot] com
License: MIT
Keywords: cider,homebrew,bootstrap,automation
Platform: osx
Classifier: Development Status :: 4 - Beta
Classifier: Environment :: Console
Classifier: Environment :: MacOS X
Classifier: Intended Audience :: Developers
Classifier: License :: OSI Approved :: MIT License
Classifier: Natural Language :: English
Classifier: Operating System :: MacOS :: MacOS X
Classifier: Programming Language :: Objective C
Classifier: Programming Language :: Python :: 2.7
Classifier: Topic :: Software Development
Classifier: Topic :: System
Classifier: Topic :: System :: Archiving :: Backup
Classifier: Topic :: Utilities
